unison_gitignore/__init__.py
unison_gitignore/__main__.py
unison_gitignore/main.py
unison_gitignore/parser.py
unison_gitignore/util.py
unison_gitignore-1.0.5.dist-info/LICENSE
unison_gitignore-1.0.5.dist-info/METADATA
unison_gitignore-1.0.5.dist-info/WHEEL
unison_gitignore-1.0.5.dist-info/entry_points.txt
unison_gitignore-1.0.5.dist-info/top_level.txt
unison_gitignore-1.0.5.dist-info/RECORD
